odoo10_addon_account_group_invoice_line-10.0.1.0.0-py2.7-nspkg.pth
odoo10_addon_account_group_invoice_line-10.0.1.0.0.dist-info/top_level.txt
odoo10_addon_account_group_invoice_line-10.0.1.0.0.dist-info/WHEEL
odoo10_addon_account_group_invoice_line-10.0.1.0.0.dist-info/RECORD
odoo10_addon_account_group_invoice_line-10.0.1.0.0.dist-info/metadata.json
odoo10_addon_account_group_invoice_line-10.0.1.0.0.dist-info/DESCRIPTION.rst
odoo10_addon_account_group_invoice_line-10.0.1.0.0.dist-info/METADATA
odoo10_addon_account_group_invoice_line-10.0.1.0.0.dist-info/namespace_packages.txt
odoo/addons/account_group_invoice_line/__manifest__.py
odoo/addons/account_group_invoice_line/__init__.py
odoo/addons/account_group_invoice_line/README.rst
odoo/addons/account_group_invoice_line/models/account_invoice.py
odoo/addons/account_group_invoice_line/models/account_journal.py
odoo/addons/account_group_invoice_line/models/__init__.py
odoo/addons/account_group_invoice_line/i18n/zh_CN.po
odoo/addons/account_group_invoice_line/i18n/it.po
odoo/addons/account_group_invoice_line/i18n/es.po
odoo/addons/account_group_invoice_line/i18n/sl.po
odoo/addons/account_group_invoice_line/i18n/nl.po
odoo/addons/account_group_invoice_line/i18n/account_group_invoice_lines.pot
odoo/addons/account_group_invoice_line/i18n/fr.po
odoo/addons/account_group_invoice_line/i18n/pt_BR.po
odoo/addons/account_group_invoice_line/views/account_journal.xml
