Metadata-Version: 2.0
Name: odoo10-addon-account-group-invoice-line
Version: 10.0.1.0.0
Summary: Add option to group invoice lines per account
Home-page: http://www.syleam.fr/
Author: SYLEAM,Akretion,Odoo Community Association (OCA)
Author-email: support@odoo-community.org
License: AGPL-3
Platform: UNKNOWN
Requires-Dist: odoo (<10.1dev,>=10.0)
Classifier: Programming Language :: Python :: 2.7
Classifier: Framework :: Odoo
Classifier: License :: OSI Approved :: GNU Affero General Public License v3
